[
  {
    "id": 1,
    "img": "https://images.pexels.com/photos/2762247/pexels-photo-2762247.jpeg?auto=compress&cs=tinysrgb&w=600",
    "name": "Liquidificador com Tecnologia de Ponta",
    "price": 129.99
  },
  {
    "id": 2,
    "img": "https://images.pexels.com/photos/11112735/pexels-photo-11112735.jpeg?auto=compress&cs=tinysrgb&w=600",
    "name": "Conjunto de Panelas Antiaderentes",
    "price": 199.90
  },
  {
    "id": 3,
    "img": "https://images.pexels.com/photos/11112739/pexels-photo-11112739.jpeg?auto=compress&cs=tinysrgb&w=600",
    "name": "Máquina de Café Expresso Automática",
    "price": 349.50
  },
  {
    "id": 4,
    "img": "https://images.pexels.com/photos/12502430/pexels-photo-12502430.jpeg?auto=compress&cs=tinysrgb&w=600",
    "name": "Aspirador de Pó Sem Fio",
    "price": 149.75
  },
  {
    "id": 5,
    "img": "https://images.pexels.com/photos/4618517/pexels-photo-4618517.jpeg?auto=compress&cs=tinysrgb&w=600",
    "name": "Fritadeira Elétrica Sem Óleo",
    "price": 119.99
  },
  {
    "id": 6,
    "img": "https://images.pexels.com/photos/10493902/pexels-photo-10493902.jpeg?auto=compress&cs=tinysrgb&w=600",
    "name": "Ventilador de Teto Silencioso",
    "price": 199.99
  },
  {
    "id": 7,
    "img": "https://images.pexels.com/photos/1647978/pexels-photo-1647978.jpeg?auto=compress&cs=tinysrgb&w=600",
    "name": "Smartphone Desbloqueado 128GB",
    "price": 899.00
  },
  {
    "id": 8,
    "img": "https://images.pexels.com/photos/16070479/pexels-photo-16070479/free-photo-of-console-painel-eletronicos-equipamento.jpeg?auto=compress&cs=tinysrgb&w=600",
    "name": "Cadeira Ergonômica para Escritório",
    "price": 249.95
  },
  {
    "id": 9,
    "img": "https://images.pexels.com/photos/914055/pexels-photo-914055.jpeg?auto=compress&cs=tinysrgb&w=600",
    "name": "Tapete Decorativo de Alta Qualidade",
    "price": 79.50
  },
  {
    "id": 10,
    "img": "https://images.pexels.com/photos/165978/pexels-photo-165978.jpeg?auto=compress&cs=tinysrgb&w=600",
    "name": "Câmera Fotográfica Profissional",
    "price": 599.00
  },
  {
    "id": 11,
    "img": "https://images.pexels.com/photos/5205809/pexels-photo-5205809.jpeg?auto=compress&cs=tinysrgb&w=600",
    "name": "Caixa de Som Bluetooth Resistente à Água",
    "price": 89.99
  },
  {
    "id": 12,
    "img": "https://images.pexels.com/photos/12456258/pexels-photo-12456258.jpeg?auto=compress&cs=tinysrgb&w=600",
    "name": "Tênis Esportivo Leve e Confortável",
    "price": 129.95
  },
  {
    "id": 13,
    "img": "https://images.pexels.com/photos/15827688/pexels-photo-15827688/free-photo-of-caixa-bau-arca-embalagem.jpeg?auto=compress&cs=tinysrgb&w=600",
    "name": "Mala de Viagem com Rodinhas 24\"",
    "price": 149.99
  },
  {
    "id": 14,
    "img": "https://images.pexels.com/photos/17596984/pexels-photo-17596984/free-photo-of-caixa-bau-arca-embalagem.jpeg?auto=compress&cs=tinysrgb&w=600",
    "name": "Grill Elétrico para Churrasco em Casa",
    "price": 179.50
  },
  {
    "id": 15,
    "img": "https://images.pexels.com/photos/15840650/pexels-photo-15840650/free-photo-of-eletronicos-equipamento-maquinario-aparelhos.jpeg?auto=compress&cs=tinysrgb&w=600",
    "name": "Notebook Ultraleve com Tela Full HD",
    "price": 999.00
  },
  {
    "id": 16,
    "img": "https://images.pexels.com/photos/12835317/pexels-photo-12835317.jpeg?auto=compress&cs=tinysrgb&w=600",
    "name": "Relógio Inteligente com Monitor Cardíaco",
    "price": 129.99
  }
]

